LICENSE
README.md
setup.py
wecom_bot_msg/__init__.py
wecom_bot_msg/wecom_bot.py
wecom_bot_msg.egg-info/PKG-INFO
wecom_bot_msg.egg-info/SOURCES.txt
wecom_bot_msg.egg-info/dependency_links.txt
wecom_bot_msg.egg-info/top_level.txt