Metadata-Version: 2.1
Name: wecom_bot_msg
Version: 0.1.1
Summary: A simple API wrapper for WeCom (Worker Wechat) group bot to send msg.
Home-page: https://github.com/plutotree/wecom_bot_msg_python
Author: plutotree
Author-email: plutotreetree@gmail.com
License: MIT
Classifier: Programming Language :: Python :: 3
Classifier: License :: OSI Approved :: MIT License
Requires-Python: >=3.6
License-File: LICENSE
